gcc_play/__init__.py
gcc_play/cli.py
gcc_play-0.2.0.dist-info/entry_points.txt
gcc_play-0.2.0.dist-info/WHEEL
gcc_play-0.2.0.dist-info/METADATA
gcc_play-0.2.0.dist-info/RECORD
