Metadata-Version: 2.1
Name: gcc-play
Version: 0.2.0
Summary: linux commands built with python for my own use.
License: MIT
Author: rai
Requires-Python: >=3.10,<4.0
Classifier: License :: OSI Approved :: MIT License
Classifier: Programming Language :: Python :: 3
Classifier: Programming Language :: Python :: 3.10
Requires-Dist: click (>=8.1.3,<9.0.0)
